{
  "GlobalConfiguration": {
    "BaseUrl": "https://localhost:5178"
  },
  "Routes": [
    {
      "DownstreamPathTemplate": "/api/Prueba/list",
      "DownstreamScheme": "http",
      "DownstreamHostAndPorts": [
        {
          "Host": "localhost",
          "Port": 5239
        }
      ],
      "UpstreamPathTemplate": "/Prueba/List",
      "UpstreamHttpMethod": [
        "Get"
      ]
    },
    {
      "DownstreamPathTemplate": "/api/Prueba/list",
      "DownstreamScheme": "http",
      "DownstreamHostAndPorts": [
        {
          "Host": "localhost",
          "Port": 5269
        }
      ],
      "UpstreamPathTemplate": "/Pruebagcp/List",
      "UpstreamHttpMethod": [
        "Get"
      ]
    },
    {
      "DownstreamPathTemplate": "/customers",
      "DownstreamScheme": "http",
      "DownstreamHostAndPorts": [
        {
          "Host": "localhost",
          "Port": 4036
        }
      ],
      "UpstreamPathTemplate": "/customers/data",
      "UpstreamHttpMethod": [
        "Get"
      ]
    }
  ]
}